quizblock/__init__.py
quizblock/admin.py
quizblock/apps.py
quizblock/models.py
quizblock/urls.py
quizblock/views.py
quizblock/migrations/0001_initial.py
quizblock/migrations/0002_auto_20150202_1707.py
quizblock/migrations/0003_auto_20150209_1601.py
quizblock/migrations/0004_question_css_extra.py
quizblock/migrations/0006_auto_20160613_1001.py
quizblock/migrations/__init__.py
quizblock/static/quizblock/js/quizblock-admin.js
quizblock/static/quizblock/js/quizshow.js
quizblock/templates/quizblock/answer_confirm_delete.html
quizblock/templates/quizblock/edit_answer.html
quizblock/templates/quizblock/edit_question.html
quizblock/templates/quizblock/include_jquery.html
quizblock/templates/quizblock/long_answer_show_answer.html
quizblock/templates/quizblock/long_text.html
quizblock/templates/quizblock/multiple_choice.html
quizblock/templates/quizblock/multiple_choice_show_answer.html
quizblock/templates/quizblock/question.html
quizblock/templates/quizblock/question_confirm_delete.html
quizblock/templates/quizblock/quiz_detail.html
quizblock/templates/quizblock/quizblock.html
quizblock/templates/quizblock/short_text.html
quizblock/templates/quizblock/show_answer.html
quizblock/templates/quizblock/single_choice.html
quizblock/templates/quizblock/single_choice_dropdown.html
quizblock/templates/quizblock/single_choice_show_answer.html
quizblock/templatetags/__init__.py
quizblock/templatetags/getresponse.py
quizblock/tests/__init__.py
quizblock/tests/test_models.py
quizblock/tests/test_reports.py
quizblock/tests/test_templatetags.py
quizblock/tests/test_views.py
django_quizblock-1.3.2.dist-info/METADATA
django_quizblock-1.3.2.dist-info/WHEEL
django_quizblock-1.3.2.dist-info/top_level.txt
django_quizblock-1.3.2.dist-info/RECORD
