Metadata-Version: 2.1
Name: django-quizblock
Version: 1.3.2
Summary: Basic Quiz PageBlock
Home-page: https://github.com/ccnmtl/django-quizblock
Author: Anders Pearson, Evan Petersen
Author-email: ctl-dev@columbia.edu
License: BSD
Platform: any
Requires-Dist: django-pagetree >=1.1.2
Requires-Dist: django-markdownify
